flask_ldap3_simple_auth/__init__.py
flask_ldap3_simple_auth-0.2.dist-info/METADATA
flask_ldap3_simple_auth-0.2.dist-info/WHEEL
flask_ldap3_simple_auth-0.2.dist-info/top_level.txt
flask_ldap3_simple_auth-0.2.dist-info/RECORD
