Metadata-Version: 2.1
Name: flask-ldap3-simple-auth
Version: 0.2
Requires-Dist: ldap3
Requires-Dist: Flask
